setup.py
nekit_krasava/__init__.py
nekit_krasava/one.py
nekit_krasava/two.py
nekit_krasava.egg-info/PKG-INFO
nekit_krasava.egg-info/SOURCES.txt
nekit_krasava.egg-info/dependency_links.txt
nekit_krasava.egg-info/top_level.txt