Metadata-Version: 2.1
Name: nekit_krasava
Version: 0.0.1
Summary: So Package
Author: Nekit Yo
Author-email: your@gmail.com
